{
  "doubleclick.net": "Google DoubleClick Ads",
  "googlesyndication.com": "Google AdSense",
  "googleadservices.com": "Google Ad Services",
  "googletagmanager.com": "Google Tag Manager",
  "google-analytics.com": "Google Analytics",
  "ssl.google-analytics.com": "Google Analytics SSL",
  "analytics.google.com": "Google Analytics 4",
  "app-measurement.com": "Firebase App Measurement",
  "firebase.google.com": "Firebase Analytics",
  "firebaselogging.googleapis.com": "Firebase Logging",
  "connect.facebook.net": "Facebook SDK",
  "graph.facebook.com": "Facebook Graph API",
  "an.facebook.com": "Facebook Audience Network",
  "analytics.facebook.com": "Facebook Analytics",
  "api.mixpanel.com": "Mixpanel Analytics",
  "decide.mixpanel.com": "Mixpanel Decide",
  "api.amplitude.com": "Amplitude Analytics",
  "api2.amplitude.com": "Amplitude Analytics v2",
  "flurry.com": "Yahoo Flurry Analytics",
  "data.flurry.com": "Flurry Data",
  "t.appsflyer.com": "AppsFlyer Attribution",
  "impression.appsflyer.com": "AppsFlyer Impression",
  "app.adjust.com": "Adjust Attribution",
  "s2s.adjust.com": "Adjust S2S",
  "adjust.com": "Adjust SDK",
  "api.branch.io": "Branch Attribution",
  "bnc.lt": "Branch Short Links",
  "control.kochava.com": "Kochava Attribution",
  "sdk-api.singular.net": "Singular Attribution",
  "onesignal.com": "OneSignal Push",
  "api.onesignal.com": "OneSignal API",
  "fcm.googleapis.com": "Firebase Cloud Messaging",
  "mtalk.google.com": "Google Push FCM",
  "sentry.io": "Sentry Error Tracking",
  "reports.crashlytics.com": "Firebase Crashlytics",
  "hotjar.com": "Hotjar Heatmaps",
  "fullstory.com": "FullStory Session Recording",
  "logrocket.com": "LogRocket Session Recording",
  "segment.com": "Segment CDP",
  "api.segment.io": "Segment API",
  "heapanalytics.com": "Heap Analytics",
  "mopub.com": "Twitter MoPub Ads",
  "inmobi.com": "InMobi Ads",
  "admob.com": "Google AdMob",
  "applovin.com": "AppLovin Ads",
  "chartboost.com": "Chartboost Ads",
  "ironsrc.com": "ironSource Ads",
  "unity3d.com": "Unity Ads",
  "vungle.com": "Vungle Video Ads",
  "adcolony.com": "AdColony Ads",
  "criteo.com": "Criteo Retargeting",
  "taboola.com": "Taboola Ads",
  "outbrain.com": "Outbrain Ads",
  "scorecardresearch.com": "Comscore Research",
  "quantserve.com": "Quantcast",
  "bluekai.com": "Oracle BlueKai",
  "addthis.com": "AddThis Tracker",
  "sharethis.com": "ShareThis Tracker",
  "ads.twitter.com": "Twitter Ads",
  "braze.com": "Braze Push",
  "customer.io": "Customer.io Push",
  "intercom.io": "Intercom Analytics",
  "newrelic.com": "New Relic APM",
  "datadoghq.com": "Datadog APM",
  "bugsnag.com": "Bugsnag Error Tracking",
  "rollbar.com": "Rollbar Error Tracking",
  "snapkit.snapchat.com": "Snapchat SDK",
  "smartlook.com": "Smartlook Recording",
  "mouseflow.com": "Mouseflow Recording",
  "moatads.com": "Moat Ad Verification",
  "rubiconproject.com": "Rubicon Ads",
  "pubmatic.com": "PubMatic Exchange",
  "openx.net": "OpenX Exchange",
  "appnexus.com": "Xandr Ads",
  "go.onelink.me": "AppsFlyer OneLink",
  "urbanairship.com": "Airship Push",
  "localytics.com": "Localytics Analytics",
  "swrve.com": "Swrve Analytics",
  "startappservice.com": "StartApp Ads",
  "smartadserver.com": "Smart Ad Server",
  "advertising.apple.com": "Apple Advertising",
  "stats.pusher.com": "Pusher Stats"
}